django_email_throttler/__init__.py
django_email_throttler/throttler.py
django_email_throttler/management/__init__.py
django_email_throttler/management/commands/__init__.py
django_email_throttler/management/commands/throttle_report.py
django_email_throttler-0.5.0.dist-info/LICENSE
django_email_throttler-0.5.0.dist-info/METADATA
django_email_throttler-0.5.0.dist-info/WHEEL
django_email_throttler-0.5.0.dist-info/top_level.txt
django_email_throttler-0.5.0.dist-info/RECORD
