Metadata-Version: 2.1
Name: django-email-throttler
Version: 0.5.0
Summary: An email throttler for Django
Home-page: https://github.com/robert-kisteleki/django-email-throttler
Download-URL: https://github.com/robert-kisteleki/django-email-throttler
Author: Robert Kisteleki
Author-email: kistel@gmail.com
License: GPLv3
Keywords: Django,email
Classifier: License :: OSI Approved :: GNU General Public License v3 (GPLv3)
Classifier: Operating System :: POSIX
Classifier: Operating System :: Unix
Classifier: Programming Language :: Python
Classifier: Programming Language :: Python :: 3
Classifier: Programming Language :: Python :: Implementation :: CPython
Classifier: Programming Language :: Python :: Implementation :: PyPy
License-File: LICENSE
